grafo/__init__.py
grafo/components.py
grafo/errors.py
grafo/executor.py
grafo/_internal/__init__.py
grafo/_internal/dataclasses.py
grafo/_internal/logger.py
grafo/_internal/protocols.py
grafo-0.3.3.dist-info/licenses/LICENSE.txt
grafo-0.3.3.dist-info/METADATA
grafo-0.3.3.dist-info/WHEEL
grafo-0.3.3.dist-info/top_level.txt
grafo-0.3.3.dist-info/RECORD
