Metadata-Version: 2.4
Name: grafo
Version: 0.3.3
Summary: A library for building runnable asynchronous trees
Author-email: "@paulomtts" <paulomtts@outlook.com>
License: MIT
Project-URL: Homepage, https://github.com/paulomtts/grafo
Keywords: asynchronous,trees,library
Classifier: Programming Language :: Python :: 3
Classifier: License :: OSI Approved :: MIT License
Classifier: Operating System :: OS Independent
Requires-Python: >=3.10
License-File: LICENSE.txt
Requires-Dist: bump2version>=1.0.1
Requires-Dist: pytest-asyncio>=0.16.0
Requires-Dist: pytest>=7.0.1
Requires-Dist: ruff>=0.0.17
Requires-Dist: mkdocs>=1.0.1
Requires-Dist: mkdocs-material>=9.0.0
Requires-Dist: mkdocstrings[python]>=0.24.0
Dynamic: license-file
